falconx_py/__init__.py
falconx_py/client.py
falconx_py/secrets.py
falconx_py-0.2.dist-info/LICENSE
falconx_py-0.2.dist-info/METADATA
falconx_py-0.2.dist-info/WHEEL
falconx_py-0.2.dist-info/top_level.txt
falconx_py-0.2.dist-info/RECORD
