Metadata-Version: 2.1
Name: falconx-py
Version: 0.2
Summary: The official client for the FalconX API
Home-page: https://github.com/falconxio/falconx-py
Author: FalconX
Author-email: support@falconx.io
License: UNKNOWN
Platform: UNKNOWN
Classifier: Programming Language :: Python :: 3
Classifier: License :: OSI Approved :: MIT License
Classifier: Operating System :: OS Independent
